{"name":"dojo-obby","className":"DataModel","filePaths":["default.project.json"],"children":[{"name":"HttpService","className":"HttpService"},{"name":"Lighting","className":"Lighting"},{"name":"ReplicatedStorage","className":"ReplicatedStorage","children":[{"name":"Assets","className":"Folder","children":[{"name":"Images","className":"ModuleScript","filePaths":["src/shared\\Assets\\Images.lua"]},{"name":"Sounds","className":"ModuleScript","filePaths":["src/shared\\Assets\\Sounds.lua"]}]},{"name":"Components","className":"Folder"},{"name":"FusionMaterial","className":"Folder","children":[{"name":"CheckpointNotification","className":"ModuleScript","filePaths":["src/shared\\FusionMaterial\\CheckpointNotification.lua"]}]},{"name":"Interface","className":"ModuleScript","filePaths":["src/shared\\Interface.lua"]},{"name":"Modules","className":"Folder","children":[{"name":"Tween","className":"ModuleScript","filePaths":["src/shared\\Modules\\Tween.lua"]}]},{"name":"State","className":"ModuleScript","filePaths":["src/shared\\State.lua"]},{"name":"Packages","className":"Folder","children":[{"name":"Component","className":"ModuleScript","filePaths":["Packages\\Component.lua"]},{"name":"Fusion","className":"ModuleScript","filePaths":["Packages\\Fusion.lua"]},{"name":"Promise","className":"ModuleScript","filePaths":["Packages\\Promise.lua"]},{"name":"Red","className":"ModuleScript","filePaths":["Packages\\Red.lua"]},{"name":"Rewire","className":"ModuleScript","filePaths":["Packages\\Rewire.lua"]},{"name":"Trove","className":"ModuleScript","filePaths":["Packages\\Trove.lua"]},{"name":"_Index","className":"Folder","children":[{"name":"elttob_fusion@0.2.0","className":"Folder","children":[{"name":"fusion","className":"ModuleScript","filePaths":["Packages\\_Index\\elttob_fusion@0.2.0\\fusion\\src\\init.lua","Packages\\_Index\\elttob_fusion@0.2.0\\fusion\\default.project.json"],"children":[{"name":"Animation","className":"Folder","children":[{"name":"Spring","className":"ModuleScript","filePaths":["Packages\\_Index\\elttob_fusion@0.2.0\\fusion\\src\\Animation\\Spring.lua"]},{"name":"SpringScheduler","className":"ModuleScript","filePaths":["Packages\\_Index\\elttob_fusion@0.2.0\\fusion\\src\\Animation\\SpringScheduler.lua"]},{"name":"Tween","className":"ModuleScript","filePaths":["Packages\\_Index\\elttob_fusion@0.2.0\\fusion\\src\\Animation\\Tween.lua"]},{"name":"TweenScheduler","className":"ModuleScript","filePaths":["Packages\\_Index\\elttob_fusion@0.2.0\\fusion\\src\\Animation\\TweenScheduler.lua"]},{"name":"getTweenRatio","className":"ModuleScript","filePaths":["Packages\\_Index\\elttob_fusion@0.2.0\\fusion\\src\\Animation\\getTweenRatio.lua"]},{"name":"lerpType","className":"ModuleScript","filePaths":["Packages\\_Index\\elttob_fusion@0.2.0\\fusion\\src\\Animation\\lerpType.lua"]},{"name":"packType","className":"ModuleScript","filePaths":["Packages\\_Index\\elttob_fusion@0.2.0\\fusion\\src\\Animation\\packType.lua"]},{"name":"springCoefficients","className":"ModuleScript","filePaths":["Packages\\_Index\\elttob_fusion@0.2.0\\fusion\\src\\Animation\\springCoefficients.lua"]},{"name":"unpackType","className":"ModuleScript","filePaths":["Packages\\_Index\\elttob_fusion@0.2.0\\fusion\\src\\Animation\\unpackType.lua"]}]},{"name":"Colour","className":"Folder","children":[{"name":"Oklab","className":"ModuleScript","filePaths":["Packages\\_Index\\elttob_fusion@0.2.0\\fusion\\src\\Colour\\Oklab.lua"]}]},{"name":"Dependencies","className":"Folder","children":[{"name":"captureDependencies","className":"ModuleScript","filePaths":["Packages\\_Index\\elttob_fusion@0.2.0\\fusion\\src\\Dependencies\\captureDependencies.lua"]},{"name":"initDependency","className":"ModuleScript","filePaths":["Packages\\_Index\\elttob_fusion@0.2.0\\fusion\\src\\Dependencies\\initDependency.lua"]},{"name":"sharedState","className":"ModuleScript","filePaths":["Packages\\_Index\\elttob_fusion@0.2.0\\fusion\\src\\Dependencies\\sharedState.lua"]},{"name":"updateAll","className":"ModuleScript","filePaths":["Packages\\_Index\\elttob_fusion@0.2.0\\fusion\\src\\Dependencies\\updateAll.lua"]},{"name":"useDependency","className":"ModuleScript","filePaths":["Packages\\_Index\\elttob_fusion@0.2.0\\fusion\\src\\Dependencies\\useDependency.lua"]}]},{"name":"Instances","className":"Folder","children":[{"name":"Children","className":"ModuleScript","filePaths":["Packages\\_Index\\elttob_fusion@0.2.0\\fusion\\src\\Instances\\Children.lua"]},{"name":"Cleanup","className":"ModuleScript","filePaths":["Packages\\_Index\\elttob_fusion@0.2.0\\fusion\\src\\Instances\\Cleanup.lua"]},{"name":"Hydrate","className":"ModuleScript","filePaths":["Packages\\_Index\\elttob_fusion@0.2.0\\fusion\\src\\Instances\\Hydrate.lua"]},{"name":"New","className":"ModuleScript","filePaths":["Packages\\_Index\\elttob_fusion@0.2.0\\fusion\\src\\Instances\\New.lua"]},{"name":"OnChange","className":"ModuleScript","filePaths":["Packages\\_Index\\elttob_fusion@0.2.0\\fusion\\src\\Instances\\OnChange.lua"]},{"name":"OnEvent","className":"ModuleScript","filePaths":["Packages\\_Index\\elttob_fusion@0.2.0\\fusion\\src\\Instances\\OnEvent.lua"]},{"name":"Out","className":"ModuleScript","filePaths":["Packages\\_Index\\elttob_fusion@0.2.0\\fusion\\src\\Instances\\Out.lua"]},{"name":"Ref","className":"ModuleScript","filePaths":["Packages\\_Index\\elttob_fusion@0.2.0\\fusion\\src\\Instances\\Ref.lua"]},{"name":"applyInstanceProps","className":"ModuleScript","filePaths":["Packages\\_Index\\elttob_fusion@0.2.0\\fusion\\src\\Instances\\applyInstanceProps.lua"]},{"name":"defaultProps","className":"ModuleScript","filePaths":["Packages\\_Index\\elttob_fusion@0.2.0\\fusion\\src\\Instances\\defaultProps.lua"]}]},{"name":"Logging","className":"Folder","children":[{"name":"logError","className":"ModuleScript","filePaths":["Packages\\_Index\\elttob_fusion@0.2.0\\fusion\\src\\Logging\\logError.lua"]},{"name":"logErrorNonFatal","className":"ModuleScript","filePaths":["Packages\\_Index\\elttob_fusion@0.2.0\\fusion\\src\\Logging\\logErrorNonFatal.lua"]},{"name":"logWarn","className":"ModuleScript","filePaths":["Packages\\_Index\\elttob_fusion@0.2.0\\fusion\\src\\Logging\\logWarn.lua"]},{"name":"messages","className":"ModuleScript","filePaths":["Packages\\_Index\\elttob_fusion@0.2.0\\fusion\\src\\Logging\\messages.lua"]},{"name":"parseError","className":"ModuleScript","filePaths":["Packages\\_Index\\elttob_fusion@0.2.0\\fusion\\src\\Logging\\parseError.lua"]}]},{"name":"PubTypes","className":"ModuleScript","filePaths":["Packages\\_Index\\elttob_fusion@0.2.0\\fusion\\src\\PubTypes.lua"]},{"name":"State","className":"Folder","children":[{"name":"Computed","className":"ModuleScript","filePaths":["Packages\\_Index\\elttob_fusion@0.2.0\\fusion\\src\\State\\Computed.lua"]},{"name":"ForKeys","className":"ModuleScript","filePaths":["Packages\\_Index\\elttob_fusion@0.2.0\\fusion\\src\\State\\ForKeys.lua"]},{"name":"ForPairs","className":"ModuleScript","filePaths":["Packages\\_Index\\elttob_fusion@0.2.0\\fusion\\src\\State\\ForPairs.lua"]},{"name":"ForValues","className":"ModuleScript","filePaths":["Packages\\_Index\\elttob_fusion@0.2.0\\fusion\\src\\State\\ForValues.lua"]},{"name":"Observer","className":"ModuleScript","filePaths":["Packages\\_Index\\elttob_fusion@0.2.0\\fusion\\src\\State\\Observer.lua"]},{"name":"Value","className":"ModuleScript","filePaths":["Packages\\_Index\\elttob_fusion@0.2.0\\fusion\\src\\State\\Value.lua"]},{"name":"unwrap","className":"ModuleScript","filePaths":["Packages\\_Index\\elttob_fusion@0.2.0\\fusion\\src\\State\\unwrap.lua"]}]},{"name":"Types","className":"ModuleScript","filePaths":["Packages\\_Index\\elttob_fusion@0.2.0\\fusion\\src\\Types.lua"]},{"name":"Utility","className":"Folder","children":[{"name":"None","className":"ModuleScript","filePaths":["Packages\\_Index\\elttob_fusion@0.2.0\\fusion\\src\\Utility\\None.lua"]},{"name":"cleanup","className":"ModuleScript","filePaths":["Packages\\_Index\\elttob_fusion@0.2.0\\fusion\\src\\Utility\\cleanup.lua"]},{"name":"doNothing","className":"ModuleScript","filePaths":["Packages\\_Index\\elttob_fusion@0.2.0\\fusion\\src\\Utility\\doNothing.lua"]},{"name":"isSimilar","className":"ModuleScript","filePaths":["Packages\\_Index\\elttob_fusion@0.2.0\\fusion\\src\\Utility\\isSimilar.lua"]},{"name":"needsDestruction","className":"ModuleScript","filePaths":["Packages\\_Index\\elttob_fusion@0.2.0\\fusion\\src\\Utility\\needsDestruction.lua"]},{"name":"restrictRead","className":"ModuleScript","filePaths":["Packages\\_Index\\elttob_fusion@0.2.0\\fusion\\src\\Utility\\restrictRead.lua"]},{"name":"xtypeof","className":"ModuleScript","filePaths":["Packages\\_Index\\elttob_fusion@0.2.0\\fusion\\src\\Utility\\xtypeof.lua"]}]}]}]},{"name":"evaera_promise@4.0.0","className":"Folder","children":[{"name":"promise","className":"ModuleScript","filePaths":["Packages\\_Index\\evaera_promise@4.0.0\\promise\\lib\\init.lua","Packages\\_Index\\evaera_promise@4.0.0\\promise\\default.project.json"],"children":[{"name":"init.spec","className":"ModuleScript","filePaths":["Packages\\_Index\\evaera_promise@4.0.0\\promise\\lib\\init.spec.lua"]}]}]},{"name":"sayhisam1_rewire@0.3.0","className":"Folder","children":[{"name":"rewire","className":"ModuleScript","filePaths":["Packages\\_Index\\sayhisam1_rewire@0.3.0\\rewire\\src\\init.lua","Packages\\_Index\\sayhisam1_rewire@0.3.0\\rewire\\default.project.json"],"children":[{"name":"Constants","className":"ModuleScript","filePaths":["Packages\\_Index\\sayhisam1_rewire@0.3.0\\rewire\\src\\Constants.lua"]},{"name":"HotReloader","className":"ModuleScript","filePaths":["Packages\\_Index\\sayhisam1_rewire@0.3.0\\rewire\\src\\HotReloader.lua"]}]}]},{"name":"sleitnick_component@2.4.6","className":"Folder","children":[{"name":"Promise","className":"ModuleScript","filePaths":["Packages\\_Index\\sleitnick_component@2.4.6\\Promise.lua"]},{"name":"Signal","className":"ModuleScript","filePaths":["Packages\\_Index\\sleitnick_component@2.4.6\\Signal.lua"]},{"name":"Symbol","className":"ModuleScript","filePaths":["Packages\\_Index\\sleitnick_component@2.4.6\\Symbol.lua"]},{"name":"Trove","className":"ModuleScript","filePaths":["Packages\\_Index\\sleitnick_component@2.4.6\\Trove.lua"]},{"name":"component","className":"ModuleScript","filePaths":["Packages\\_Index\\sleitnick_component@2.4.6\\component\\init.lua"],"children":[{"name":"init.spec","className":"ModuleScript","filePaths":["Packages\\_Index\\sleitnick_component@2.4.6\\component\\init.spec.lua"]}]}]},{"name":"sleitnick_signal@1.5.0","className":"Folder","children":[{"name":"signal","className":"ModuleScript","filePaths":["Packages\\_Index\\sleitnick_signal@1.5.0\\signal\\init.lua"],"children":[{"name":"init.spec","className":"ModuleScript","filePaths":["Packages\\_Index\\sleitnick_signal@1.5.0\\signal\\init.spec.lua"]}]}]},{"name":"sleitnick_symbol@2.0.1","className":"Folder","children":[{"name":"symbol","className":"ModuleScript","filePaths":["Packages\\_Index\\sleitnick_symbol@2.0.1\\symbol\\init.lua"],"children":[{"name":"init.spec","className":"ModuleScript","filePaths":["Packages\\_Index\\sleitnick_symbol@2.0.1\\symbol\\init.spec.lua"]}]}]},{"name":"sleitnick_trove@0.4.2","className":"Folder","children":[{"name":"trove","className":"ModuleScript","filePaths":["Packages\\_Index\\sleitnick_trove@0.4.2\\trove\\init.lua"],"children":[{"name":"init.spec","className":"ModuleScript","filePaths":["Packages\\_Index\\sleitnick_trove@0.4.2\\trove\\init.spec.lua"]}]}]},{"name":"sleitnick_trove@0.5.0","className":"Folder","children":[{"name":"trove","className":"ModuleScript","filePaths":["Packages\\_Index\\sleitnick_trove@0.5.0\\trove\\init.lua"],"children":[{"name":"init.spec","className":"ModuleScript","filePaths":["Packages\\_Index\\sleitnick_trove@0.5.0\\trove\\init.spec.lua"]}]}]},{"name":"uncontained0_red@1.2.2","className":"Folder","children":[{"name":"red","className":"ModuleScript","filePaths":["Packages\\_Index\\uncontained0_red@1.2.2\\red\\lib\\init.luau","Packages\\_Index\\uncontained0_red@1.2.2\\red\\default.project.json"],"children":[{"name":"Net","className":"ModuleScript","filePaths":["Packages\\_Index\\uncontained0_red@1.2.2\\red\\lib\\Net\\init.luau"],"children":[{"name":"Event","className":"ModuleScript","filePaths":["Packages\\_Index\\uncontained0_red@1.2.2\\red\\lib\\Net\\Event.luau"]},{"name":"Serdes","className":"ModuleScript","filePaths":["Packages\\_Index\\uncontained0_red@1.2.2\\red\\lib\\Net\\Serdes.luau"]}]},{"name":"Util","className":"Folder","children":[{"name":"Bin","className":"ModuleScript","filePaths":["Packages\\_Index\\uncontained0_red@1.2.2\\red\\lib\\Util\\Bin.luau"]},{"name":"Clock","className":"ModuleScript","filePaths":["Packages\\_Index\\uncontained0_red@1.2.2\\red\\lib\\Util\\Clock.luau"]},{"name":"Collection","className":"ModuleScript","filePaths":["Packages\\_Index\\uncontained0_red@1.2.2\\red\\lib\\Util\\Collection.luau"]},{"name":"Promise","className":"ModuleScript","filePaths":["Packages\\_Index\\uncontained0_red@1.2.2\\red\\lib\\Util\\Promise.luau"]},{"name":"Ratelimit","className":"ModuleScript","filePaths":["Packages\\_Index\\uncontained0_red@1.2.2\\red\\lib\\Util\\Ratelimit.luau"]},{"name":"Signal","className":"ModuleScript","filePaths":["Packages\\_Index\\uncontained0_red@1.2.2\\red\\lib\\Util\\Signal.luau"]},{"name":"Spawn","className":"ModuleScript","filePaths":["Packages\\_Index\\uncontained0_red@1.2.2\\red\\lib\\Util\\Spawn.luau"]}]}]}]}]}]}]},{"name":"ServerScriptService","className":"ServerScriptService","children":[{"name":"Components","className":"Folder","children":[{"name":"Checkpoint","className":"ModuleScript","filePaths":["src/server\\Components\\Checkpoint.lua"]},{"name":"KillBrick","className":"ModuleScript","filePaths":["src/server\\Components\\KillBrick.lua"]}]},{"name":"Modules","className":"Folder","children":[{"name":"StatsModule","className":"ModuleScript","filePaths":["src/server\\Modules\\StatsModule.lua"]}]},{"name":"ServerInit","className":"Script","filePaths":["src/server\\ServerInit.server.lua"]},{"name":"reloader","className":"LocalScript","filePaths":["src/server\\reloader.client.lua"]},{"name":"Packages","className":"Folder","children":[{"name":"ProfileService","className":"ModuleScript","filePaths":["ServerPackages\\ProfileService.lua"]},{"name":"_Index","className":"Folder","children":[{"name":"firecam702_profileservice@1.0.0","className":"Folder","children":[{"name":"profileservice","className":"ModuleScript","filePaths":["ServerPackages\\_Index\\firecam702_profileservice@1.0.0\\profileservice\\src\\init.lua","ServerPackages\\_Index\\firecam702_profileservice@1.0.0\\profileservice\\default.project.json"]}]}]}]}]},{"name":"ServerStorage","className":"ServerStorage"},{"name":"StarterPlayer","className":"StarterPlayer","children":[{"name":"StarterPlayerScripts","className":"StarterPlayerScripts","children":[{"name":"ClientInit","className":"LocalScript","filePaths":["src/client\\ClientInit.client.lua"]},{"name":"Components","className":"Folder"}]}]},{"name":"Workspace","className":"Workspace"}]}